Metadata-Version: 1.0
Name: hausdorff
Version: 0.2.4
Summary: UNKNOWN
Home-page: UNKNOWN
Author: mavillan
Author-email: nallivam@gmail.com
License: GNU GENERAL PUBLIC LICENSE Version 3
Platform: UNKNOWN
